setup.py
asyncws/__init__.py
asyncws/exceptions.py
asyncws/protocol.py
asyncws.egg-info/PKG-INFO
asyncws.egg-info/SOURCES.txt
asyncws.egg-info/dependency_links.txt
asyncws.egg-info/top_level.txt