Metadata-Version: 1.0
Name: asyncws
Version: 0.1
Summary: Websockets for python 3 (RFC 6455)
Home-page: https://github.com/BrechtBa/asyncws
Author: Brecht Baeten
Author-email: brecht.baeten@gmail.com
License: MIT
Platform: all
